remote_kernel_provider/__init__.py
remote_kernel_provider/_version.py
remote_kernel_provider/container.py
remote_kernel_provider/launcher.py
remote_kernel_provider/lifecycle_manager.py
remote_kernel_provider/manager.py
remote_kernel_provider/provider.py
remote_kernel_provider/spec_utils.py
remote_kernel_provider/kernel-launchers/python/scripts/launch_ipykernel.py
remote_kernel_provider/kernel-launchers/r/scripts/gateway_listener.py
remote_kernel_provider/kernel-launchers/r/scripts/launch_IRkernel.R
remote_kernel_provider/kernel-launchers/scala/lib/toree-assembly-0.3.0-incubating.jar
remote_kernel_provider/kernel-launchers/scala/lib/toree-launcher_2.11-0.3.0.SNAPSHOT.jar
remote_kernel_provider/kernel-resources/python/logo-64x64.png
remote_kernel_provider/kernel-resources/r/kernel.js
remote_kernel_provider/kernel-resources/r/logo-64x64.png
remote_kernel_provider/kernel-resources/scala/logo-64x64.png
remote_kernel_provider/kernel-resources/tensorflow/logo-64x64.png
remote_kernel_provider/tests/__init__.py
remote_kernel_provider/tests/conftest.py
remote_kernel_provider/tests/test_provider.py
remote_kernel_provider/tests/test_spec_utils.py
remote_kernel_provider-0.3.0.dist-info/LICENSE
remote_kernel_provider-0.3.0.dist-info/METADATA
remote_kernel_provider-0.3.0.dist-info/WHEEL
remote_kernel_provider-0.3.0.dist-info/top_level.txt
remote_kernel_provider-0.3.0.dist-info/RECORD
